stevesockets/__init__.py
stevesockets/listeners.py
stevesockets/messages.py
stevesockets/server.py
stevesockets/socketconnection.py
stevesockets/websocket.py
stevesockets-0.0.8.dist-info/METADATA
stevesockets-0.0.8.dist-info/WHEEL
stevesockets-0.0.8.dist-info/top_level.txt
stevesockets-0.0.8.dist-info/RECORD
