Metadata-Version: 2.1
Name: stevesockets
Version: 0.0.8
Summary: A simple socket and websocket server package
Home-page: https://github.com/sjb9774/stevesockets
Author: Stephen Biston
Author-email: sjb9774@gmail.com
License: UNKNOWN
Keywords: socket sockets websocket steve
Platform: UNKNOWN
Classifier: Development Status :: 3 - Alpha
Classifier: Intended Audience :: Developers
Classifier: Programming Language :: Python :: 3
Classifier: Programming Language :: Python :: 3.4
Classifier: Programming Language :: Python :: 3.5
Classifier: Programming Language :: Python :: 3.6
Classifier: Programming Language :: Python :: 3.7
